socketio/__init__.py
socketio/asgi.py
socketio/asyncio_client.py
socketio/asyncio_manager.py
socketio/asyncio_namespace.py
socketio/asyncio_pubsub_manager.py
socketio/asyncio_redis_manager.py
socketio/asyncio_server.py
socketio/base_manager.py
socketio/client.py
socketio/exceptions.py
socketio/kombu_manager.py
socketio/middleware.py
socketio/namespace.py
socketio/packet.py
socketio/pubsub_manager.py
socketio/redis_manager.py
socketio/server.py
socketio/tornado.py
socketio/zmq_manager.py
galileo_socketio-4.0.1.1.dist-info/LICENSE
galileo_socketio-4.0.1.1.dist-info/METADATA
galileo_socketio-4.0.1.1.dist-info/WHEEL
galileo_socketio-4.0.1.1.dist-info/top_level.txt
galileo_socketio-4.0.1.1.dist-info/RECORD
